ringxor/__init__.py
ringxor/ringxor.py
ringxor-0.0.3.5.dist-info/LICENSE
ringxor-0.0.3.5.dist-info/METADATA
ringxor-0.0.3.5.dist-info/WHEEL
ringxor-0.0.3.5.dist-info/top_level.txt
ringxor-0.0.3.5.dist-info/RECORD
